setup.cfg
setup.py
pythoggl/main.py
pythoggl/models.py
pythoggl/togglexceptions.py
pythoggl/togglwrapper.py
pythoggl.egg-info/PKG-INFO
pythoggl.egg-info/SOURCES.txt
pythoggl.egg-info/dependency_links.txt
pythoggl.egg-info/not-zip-safe
pythoggl.egg-info/top_level.txt