Metadata-Version: 1.1
Name: pythoggl
Version: 0.2
Summary: Just a simple wrapper for toggl
Home-page: https://github.com/whitesmith/pythoggl
Author: Nuno Lopes
Author-email: nunolopesrb@gmail.com
License: MIT
Download-URL: https://github.com/whitesmith/pythoggl/archive/0.1.tar.gz
Platform: UNKNOWN
